bulksms/__init__.py
bulksms/apps.py
bulksms/client.py
bulksms/exceptions.py
bulksms/models.py
bulksms/utils.py
bulksms/management/__init__.py
bulksms/management/commands/__init__.py
bulksms/management/commands/test_sms.py
django_bulksms_bd-0.1.1.dist-info/licenses/LICENSE
django_bulksms_bd-0.1.1.dist-info/METADATA
django_bulksms_bd-0.1.1.dist-info/WHEEL
django_bulksms_bd-0.1.1.dist-info/entry_points.txt
django_bulksms_bd-0.1.1.dist-info/top_level.txt
django_bulksms_bd-0.1.1.dist-info/RECORD
