Metadata-Version: 2.4
Name: Django-BulkSMS-BD
Version: 0.1.1
Summary: A Django package for integrating with BulkSMSBD.net SMS API
Home-page: https://github.com/sharf-shawon/django-bulksms-bd
Author: Sharfuddin Shawon
Author-email: Sharfuddin Shawon <sharf@shawon.me>
Maintainer-email: Sharfuddin Shawon <sharf@shawon.me>
License: MIT License
Project-URL: Homepage, https://github.com/sharf-shawon/django-bulksms-bd
Project-URL: Repository, https://github.com/sharf-shawon/django-bulksms-bd.git
Project-URL: Bug Tracker, https://github.com/sharf-shawon/django-bulksms-bd/issues
Project-URL: Changelog, https://github.com/sharf-shawon/django-bulksms-bd/blob/main/CHANGELOG.md
Keywords: django,sms,bulksms,bangladesh,api,messaging,verification,notifications,OTP
Classifier: Development Status :: 4 - Beta
Classifier: Environment :: Web Environment
Classifier: Framework :: Django
Classifier: Framework :: Django :: 3.2
Classifier: Framework :: Django :: 4.0
Classifier: Framework :: Django :: 4.1
Classifier: Framework :: Django :: 4.2
Classifier: Framework :: Django :: 5.0
Classifier: Intended Audience :: Developers
Classifier: License :: OSI Approved :: MIT License
Classifier: Operating System :: OS Independent
Classifier: Programming Language :: Python
Classifier: Programming Language :: Python :: 3
Classifier: Programming Language :: Python :: 3.8
Classifier: Programming Language :: Python :: 3.9
Classifier: Programming Language :: Python :: 3.10
Classifier: Programming Language :: Python :: 3.11
Classifier: Programming Language :: Python :: 3.12
Classifier: Topic :: Communications
Classifier: Topic :: Internet :: WWW/HTTP
Classifier: Topic :: Software Development :: Libraries :: Python Modules
Requires-Python: >=3.8
License-File: LICENSE
Requires-Dist: Django<5.1,>=3.2
Requires-Dist: requests>=2.25.0
Requires-Dist: urllib3>=1.26.0
Provides-Extra: dev
Requires-Dist: pytest>=6.0; extra == "dev"
Requires-Dist: pytest-django>=4.0; extra == "dev"
Requires-Dist: pytest-cov>=2.10; extra == "dev"
Requires-Dist: black>=21.0; extra == "dev"
Requires-Dist: flake8>=3.8; extra == "dev"
Requires-Dist: isort>=5.0; extra == "dev"
Requires-Dist: mypy>=0.800; extra == "dev"
Requires-Dist: pre-commit>=2.0; extra == "dev"
Provides-Extra: docs
Requires-Dist: sphinx>=4.0; extra == "docs"
Requires-Dist: sphinx-rtd-theme>=1.0; extra == "docs"
Requires-Dist: sphinx-autodoc-typehints>=1.12; extra == "docs"
Provides-Extra: testing
Requires-Dist: pytest>=6.0; extra == "testing"
Requires-Dist: pytest-django>=4.0; extra == "testing"
Requires-Dist: pytest-cov>=2.10; extra == "testing"
Requires-Dist: factory-boy>=3.2; extra == "testing"
Requires-Dist: responses>=0.18; extra == "testing"
Dynamic: author
Dynamic: home-page
Dynamic: license-file
Dynamic: requires-python
